Metadata-Version: 1.1
Name: gitkv
Version: 0.0.4
Summary: Use a git repo as a key-value store.
Home-page: https://github.com/edouardklein/gitkv
Author: HaiLuan Nguyen, Edouard Klein
Author-email: edouardklein@gmailnospam.com
License: AGPLv3
Download-URL: https://github.com/edouardklein/gitkv/tarball/0.0.4
Keywords: gitkv use a git repo as a key-value store.
Platform: UNKNOWN
Classifier: Programming Language :: Python :: 3.4
